web_mage/__init__.py
web_mage/__main__.py
web_mage/formats.py
web_mage/web_mage.py
web_mage-0.2.0.dist-info/LICENSE
web_mage-0.2.0.dist-info/METADATA
web_mage-0.2.0.dist-info/WHEEL
web_mage-0.2.0.dist-info/top_level.txt
web_mage-0.2.0.dist-info/RECORD
