Metadata-Version: 2.1
Name: web-mage
Version: 0.2.0
Summary: Small package that optimizes images for the web.
Home-page: https://github.com/c8bit/web-mage
Author: Caitlyn Finn
Author-email: caitlynannefinn@gmail.com
License: MIT
Platform: UNKNOWN
Classifier: License :: OSI Approved :: MIT License
Classifier: Development Status :: 3 - Alpha
Classifier: Intended Audience :: Developers
Classifier: Intended Audience :: Other Audience
Classifier: Programming Language :: Python
Classifier: Programming Language :: Python :: 3
Classifier: Programming Language :: Python :: 3.6
Classifier: Programming Language :: Python :: Implementation :: CPython
Classifier: Programming Language :: Python :: Implementation :: PyPy
Classifier: Topic :: Multimedia :: Graphics :: Graphics Conversion
Requires-Python: >=3.6.0
Requires-Dist: Pillow
